[{"CaseId":161,"CreatedOn":"2022-05-10 08:10","Description":"","EditedOn":"2022-05-18 11:11","EndingYear":"2050","FixResultFileName":"True","FixResultInfo":{"WorkTimesFolderPath":"C:\\Veda\\GAMS_WrkTIMES","GdxElasticDermands":{"GdxSelectedFile":{"FileName":"","FilePath":"","IsSelected":false},"IsApplied":true},"GdxIre":{"GdxSelectedFile":{"FileName":"","FilePath":"","IsSelected":false},"IsApplied":true,"RadioSelection":1},"GdxUseSolution":{"FixYearsUpto":"2020","GdxSelectedFile":{"FileName":"2cns","FilePath":"C:\\Veda\\GAMS_WrkTIMES\\2CNS\\GAMSSAVE\\2cns.gdx","IsSelected":true},"IsApplied":true,"RadioSelection":2},"IsApplyFixResult":true},"GAMSSourceFolder":"GAMS_SrcTIMES.v4.6.0","Name":"2CNS126Hydro","ParametricGroup":null,"ParametricGroupId":null,"PeriodsDefinition":"p5","PropertiesGroup":"DefaultProperties","PropertiesGroupId":483,"RegionGroup":"AllRegion","RegionGroupId":482,"ScenarioGroup":"2CNS126Hydro","ScenarioGroupId":487,"Solver":"cplex","SolverOptionFile":"CPLEX4","UserName":"hjs"},{"CaseId":162,"CreatedOn":"2022-05-10 08:11","Description":"","EditedOn":"2022-05-18 09:52","EndingYear":"2050","FixResultFileName":"False","FixResultInfo":{"WorkTimesFolderPath":null,"GdxElasticDermands":{"GdxSelectedFile":{"FileName":"","FilePath":"","IsSelected":false},"IsApplied":false},"GdxIre":{"GdxSelectedFile":{"FileName":"","FilePath":"","IsSelected":false},"IsApplied":false,"RadioSelection":1},"GdxUseSolution":{"FixYearsUpto":"","GdxSelectedFile":{"FileName":"","FilePath":"","IsSelected":false},"IsApplied":false,"RadioSelection":1},"IsApplyFixResult":false},"GAMSSourceFolder":"GAMS_SrcTIMES.v4.6.0","Name":"5CNS","ParametricGroup":null,"ParametricGroupId":null,"PeriodsDefinition":"p5","PropertiesGroup":"DefaultProperties","PropertiesGroupId":483,"RegionGroup":"AllRegion","RegionGroupId":482,"ScenarioGroup":"5CNS","ScenarioGroupId":490,"Solver":"cplex","SolverOptionFile":"CPLEX4","UserName":"hjs"},{"CaseId":163,"CreatedOn":"2022-05-10 08:11","Description":"","EditedOn":"2022-05-18 11:11","EndingYear":"2050","FixResultFileName":"True","FixResultInfo":{"WorkTimesFolderPath":"C:\\Veda\\GAMS_WrkTIMES","GdxElasticDermands":{"GdxSelectedFile":{"FileName":"","FilePath":"","IsSelected":false},"IsApplied":true},"GdxIre":{"GdxSelectedFile":{"FileName":"","FilePath":"","IsSelected":false},"IsApplied":true,"RadioSelection":1},"GdxUseSolution":{"FixYearsUpto":"2020","GdxSelectedFile":{"FileName":"2cns","FilePath":"C:\\Veda\\GAMS_WrkTIMES\\2CNS\\GAMSSAVE\\2cns.gdx","IsSelected":true},"IsApplied":true,"RadioSelection":2},"IsApplyFixResult":true},"GAMSSourceFolder":"GAMS_SrcTIMES.v4.6.0","Name":"2CNS50Hydro","ParametricGroup":null,"ParametricGroupId":null,"PeriodsDefinition":"p5","PropertiesGroup":"DefaultProperties","PropertiesGroupId":483,"RegionGroup":"AllRegion","RegionGroupId":482,"ScenarioGroup":"2CNS50Hydro","ScenarioGroupId":491,"Solver":"cplex","SolverOptionFile":"CPLEX4","UserName":"hjs"},{"CaseId":164,"CreatedOn":"2022-05-10 08:10","Description":"","EditedOn":"2022-05-18 11:11","EndingYear":"2050","FixResultFileName":"True","FixResultInfo":{"WorkTimesFolderPath":"C:\\Veda\\GAMS_WrkTIMES","GdxElasticDermands":{"GdxSelectedFile":{"FileName":"","FilePath":"","IsSelected":false},"IsApplied":true},"GdxIre":{"GdxSelectedFile":{"FileName":"","FilePath":"","IsSelected":false},"IsApplied":true,"RadioSelection":1},"GdxUseSolution":{"FixYearsUpto":"2020","GdxSelectedFile":{"FileName":"2cns","FilePath":"C:\\Veda\\GAMS_WrkTIMES\\2CNS\\GAMSSAVE\\2cns.gdx","IsSelected":true},"IsApplied":true,"RadioSelection":2},"IsApplyFixResult":true},"GAMSSourceFolder":"GAMS_SrcTIMES.v4.6.0","Name":"2CO2Tax","ParametricGroup":null,"ParametricGroupId":null,"PeriodsDefinition":"p5","PropertiesGroup":"DefaultProperties","PropertiesGroupId":483,"RegionGroup":"AllRegion","RegionGroupId":482,"ScenarioGroup":"2CO2Tax","ScenarioGroupId":488,"Solver":"cplex","SolverOptionFile":"CPLEX4","UserName":"hjs"},{"CaseId":165,"CreatedOn":"2022-05-10 08:09","Description":"","EditedOn":"2022-05-18 09:52","EndingYear":"2050","FixResultFileName":"False","FixResultInfo":{"WorkTimesFolderPath":null,"GdxElasticDermands":{"GdxSelectedFile":{"FileName":"","FilePath":"","IsSelected":false},"IsApplied":false},"GdxIre":{"GdxSelectedFile":{"FileName":"","FilePath":"","IsSelected":false},"IsApplied":false,"RadioSelection":1},"GdxUseSolution":{"FixYearsUpto":"","GdxSelectedFile":{"FileName":"","FilePath":"","IsSelected":false},"IsApplied":false,"RadioSelection":1},"IsApplyFixResult":false},"GAMSSourceFolder":"GAMS_SrcTIMES.v4.6.0","Name":"2CNS","ParametricGroup":null,"ParametricGroupId":null,"PeriodsDefinition":"p5","PropertiesGroup":"DefaultProperties","PropertiesGroupId":483,"RegionGroup":"AllRegion","RegionGroupId":482,"ScenarioGroup":"2CNS","ScenarioGroupId":486,"Solver":"cplex","SolverOptionFile":"CPLEX4","UserName":"hjs"},{"CaseId":166,"CreatedOn":"2022-05-10 08:09","Description":"","EditedOn":"2022-05-18 09:52","EndingYear":"2050","FixResultFileName":"False","FixResultInfo":{"WorkTimesFolderPath":null,"GdxElasticDermands":{"GdxSelectedFile":{"FileName":"","FilePath":"","IsSelected":false},"IsApplied":false},"GdxIre":{"GdxSelectedFile":{"FileName":"","FilePath":"","IsSelected":false},"IsApplied":false,"RadioSelection":1},"GdxUseSolution":{"FixYearsUpto":"","GdxSelectedFile":{"FileName":"","FilePath":"","IsSelected":false},"IsApplied":false,"RadioSelection":1},"IsApplyFixResult":false},"GAMSSourceFolder":"GAMS_SrcTIMES.v4.6.0","Name":"1CNS","ParametricGroup":null,"ParametricGroupId":null,"PeriodsDefinition":"p5","PropertiesGroup":"DefaultProperties","PropertiesGroupId":483,"RegionGroup":"AllRegion","RegionGroupId":482,"ScenarioGroup":"1CNS","ScenarioGroupId":492,"Solver":"cplex","SolverOptionFile":"CPLEX4","UserName":"hjs"},{"CaseId":167,"CreatedOn":"2022-05-10 08:10","Description":"","EditedOn":"2022-05-18 11:11","EndingYear":"2050","FixResultFileName":"True","FixResultInfo":{"WorkTimesFolderPath":"C:\\Veda\\GAMS_WrkTIMES","GdxElasticDermands":{"GdxSelectedFile":{"FileName":"","FilePath":"","IsSelected":false},"IsApplied":true},"GdxIre":{"GdxSelectedFile":{"FileName":"","FilePath":"","IsSelected":false},"IsApplied":true,"RadioSelection":1},"GdxUseSolution":{"FixYearsUpto":"2020","GdxSelectedFile":{"FileName":"2cns","FilePath":"C:\\Veda\\GAMS_WrkTIMES\\2CNS\\GAMSSAVE\\2cns.gdx","IsSelected":true},"IsApplied":true,"RadioSelection":2},"IsApplyFixResult":true},"GAMSSourceFolder":"GAMS_SrcTIMES.v4.6.0","Name":"2CNS_RusEmb","ParametricGroup":null,"ParametricGroupId":null,"PeriodsDefinition":"p5","PropertiesGroup":"DefaultProperties","PropertiesGroupId":483,"RegionGroup":"AllRegion","RegionGroupId":482,"ScenarioGroup":"2CNS_RusEmb","ScenarioGroupId":484,"Solver":"cplex","SolverOptionFile":"CPLEX4","UserName":"hjs"}]