{"ApplicationVersion":"1.250.1.1","UserName":"hjs","Date":"2022-04-28 08:54","FormSettings":{"DimensionsWithColumnsInfo":{"timeslice":{"Select":27,"Name":144},"region":{"Select":85,"Name":439},"scenario":{"Select":85,"Name":513},"period":{"Select":27,"Name":139},"process":{"Select":27,"Name":120,"Description":51},"commodity":{"Select":27,"Name":73,"Description":99},"userconstraint":{"Select":201,"Name":320,"Description":788},"attribute":{"Select":27,"Name":87,"Description":84},"commodityset":{"Select":27,"Name":75,"Description":73},"processset":{"Select":85,"Name":212,"Description":315},"vintage":{"Select":27,"Name":147},"studyname":{"Select":1505,"Name":13637}}}}